xcs/bitstrings.py
xcs/problems.py
xcs/scenarios.py
xcs/test_MUXProblem.py
xcs/_fast_bitstrings.py
xcs/_numpy_bitstrings.py
xcs/_python_bitstrings.py
xcs/_slow_bitstrings.py
xcs/__init__.py
xcs-1.0.0.dist-info/DESCRIPTION.rst
xcs-1.0.0.dist-info/METADATA
xcs-1.0.0.dist-info/metadata.json
xcs-1.0.0.dist-info/RECORD
xcs-1.0.0.dist-info/top_level.txt
xcs-1.0.0.dist-info/WHEEL
