Metadata-Version: 2.0
Name: xcs
Version: 1.0.0
Summary: XCS (Accuracy-based Classifier System)
Home-page: http://hosford42.github.io/xcs
Author: Aaron Hosford
Author-email: hosford42@gmail.com
License: Revised BSD
